{
    "1": [
	"WHITESUPREMACIST",
	"hihtler",
	"trans",
	"tranny",
    	"gay people",
	"females",
	"women",
	"girl",
	"female",
	"girls",
	"asians",
	"slaves",
	"cotton pickers",
	"cotton picker",
	"niger",
	"nigeria",
	"nigerians",
	"mexicans",
	"spanish people",
	"sketchful",
	"this game",
	"black people",
	"black pple",
	"blck pple",
	"blk ppl",
	"black humans",
	"black peeps",
	"black guys",
	"black guy",
	"black men",
	"black man",
	"gays",
	"LGBTQ",
	"quuers",
	"lesbians"
],
    "2": [
	"is dumb",
      "are dumb",
      "should die",
      "are slaves",
	"is a slave",
	"are greedy",
	"is greedy",
	"should burn",
	"should be burned",
	"are poor",
	"is poor",
	"should be gassed",
	"should be put in jail",
	"should be in jail",
	"should be put in prison",
	"should be in prion",
	"are rats",
	"are pigs",
	"are monkeys",
	"are monkey",
	"are monke",
	"and monkeys",
	"and monkey",
	"and monke",
	"is monkeys",
	"is monkey",
	"is monke",
	"are gorillas",
	"are chimpanzees",
	"are gorilla",
	"are chimpanzee",
	"are idiots,",
	"are idiot",
	"are slave",
	"are stupid",
	"should kill",
	"are usless",
	"are bums",
	"are gay",
	"are queer",
	"should starve",
	"aren't equal",
	"should be nuked",
	"should be locked",
	"should be set on fire",
	"should be killed",
	"should be stabbed",
	"should be murdered",
	"should be chopped",
	"should be poor",
	"should have no right",
	"should have no rights",
	"have no right",
	"have no rights",
	"has no right",
	"has no rights",
	"shouldnt marry",
	"shouldnt marry eachother",
	"shouldnt be married",
	"shouldnt be allowed",
	"sit in the back",
	"should sit in the back",
	"are minions",
	"are my minions",
	"are puppets",
	"are my puppets",
	"are junkies",
	"are  moron",
	"are  moronic",
	"are  morons",
	"should be put on",
	"should screw",
	"can suck",
	"suck my",
	"should suck"
],
    "3": [
	"kill",
	"kill all",
	"kill the",
	"kill those",
	"kill them",
	"kill these",
    	"hate",
	"hate all",
	"hate the",
	"hate them",
	"hate those",
	"hate these",
	"hurt",
	"hurt all",
	"hurt the",
	"hurt those",
	"hurt them",
	"hurt these",
	"murder",
	"murder the",
	"murder those",
	"murder all",
	"murder them",
	"murder these",
	"burn",
	"burn all",
	"burn the",
	"burn those",
	"burn them",
	"burn these",
	"shoot",
	"shoot all",
	"shoot the",
	"shoot those",
	"shoot them",
	"shoot these",
	"stab",
	"stab all",
	"stab the",
	"stab those",
	"stab them",
	"stab these",
	"I hate"
],
    "4": [
   "jews",
	"trans",
	"tranny",
    	"gay people",
	"females",
	"women",
	"girl",
	"female",
	"girls",
	"asians",
	"slaves",
	"cotton pickers",
	"cotton picker",
	"niger",
	"nigeria",
	"nigerians",
	"mexicans",
	"spanish people",
	"sketchful",
	"this game",
	"black people",
	"black pple",
	"blck pple",
	"blk ppl",
	"black humans",
	"black peeps",
	"black guys",
	"black guy",
	"black men",
	"black man",
	"gays",
	"LGBTQ",
	"quuers",
	"lesbians"

],
    "names": [
	"modbot",
	"cock",
	"minor",
	"girl",
	"boy",
	"Cock",
	"china",
	"fetsmeI",
	"[DEV]",
	"weewee",
	"diarrhea",
	"muncher",
	"hidler",
	"lickmy",
	"suckmy",
	"single",
	"heatler",
	"nuts",
	"nutz",
	"afghanistan",
	"H3NTAI",
	"hentai",
	"taliban",
	"한국 칸 (VAMPIRE)",
	"8=d",
	"b=d",
	"yourgrandfather",
	"urgrandfather",
	"yurgrandfather",
	"jurgrandfather",
	"jourgrandfather",
	"yograndfather",
	"yourgrandmother",
	"urgrandmother",
	"yurgrandmother",
	"jurgrandmother",
	"jourgrandmother",
	"yograndmother",
	"yourpops",
	"urpops",
	"yurpops",
	"jurpops",
	"jourpops",
	"yopops",
	"yourpapa",
	"urpapa",
	"yurpapa",
	"jurpapa",
	"jourpapa",
	"yopapa",
	"yourfather",
	"urfather",
	"yurfather",
	"jurfather",
	"jourfather",
	"yofather",
	"yourdad",
	"urdad",
	"yurdad",
	"jurdad",
	"jourdad",
	"yodad",
	"toxic",
	"yomom",
	"yomam",
	"yonan",
	"yomother",
	"yourmom",
	"urmom",
	"yurmom",
	"jurmom",
	"jourmom",
	"yourmam",
	"urmam",
	"yurmam",
	"jurmam",
	"jourmam",
	"yournan",
	"urnan",
	"yurnan",
	"jurnan",
	"journan",
	"yourmother",
	"urmother",
	"yurmother",
	"jurmother",
	"jourmother",
	"i love druuuugs",
	"covid",
	"covid19",
	"covidvirus",
	"covid19virus",
	"corona",
	"coronavirus",
	"titler",
	"tomboy",
	"bumbut",
	"crackhead",
	"betch",
	"shlong",
	"bussy",
	"oxmassive",
	"mikeoxmassive",
	"wanka",
	"cumsock",
	"kum",
	"poops",
	"salad",
	"fake_betch",
	"shutthe",
	"hack",
	"hacks",
	"hacks",
	"hackers",
	"hacker",
	"hackerz",
	"billy batson",
	"Дядя Жопа",
	"ligma",
	"sugma",
	"sudo rm",
	"Beauceroniney",
	"Uranus",
	"Buchachy",
	"Bürste",
	"mealgood",
	"im_Cheating",
	"ℵⅈgge℞",
	"bürste",
	"pizza.io",
	"depression",
	"depresion",
	"secsy",
	"idiot",
	"PoopyStick",
	"cheating",
	"cheater",
	"cheat",
	"cheats",
	"mikeoxlong",
	"chinese",
	"chines",
	"chineze",
	"boob",
	"boobs",
	"boobie",
	"boobies",
	"booba",
	"lend me a hug",
	"lendmeahug",
	"drug",
	"drugs",
	"drugz",
	"leZbeAn",
	"butcrack",
	"secs",
	"secks",
	"buttocks",
	"fart",
	"Lucrew",
	"ihatejustin",
	"hatejustin",
	"laserluca",
	"isrever",
	"flacid",
	"piss",
	"pissing",
	"pissed",
	"pisser",
	"racist",
	"racism",
	"minor",
	"yomom",
	"yodad",
	"yonan",
	"yomom",
	"yofather",
	"AnneFrank",
	"blackface",
	"nothin",
	"inches",
	"inchez",
	"Bunghole",
	"minor",
	"urdad",
	"yourdad",
	"slave",
	"uranus",
	"deinemuter",
	"dermuter",
	"muter",
	"yourma",
	"mother",
	"georgefloyd",
	"babe",
	"ghaybhoy",
	"date",
	"ball",
	"bals",
    "peebutt",
    "buttpee",
    "horney",
    "horny",
    "sex",
    "smexy",
    "milf",
    "gilf",
    "dilf",
    "smexy",
    "thic",
    "thick",
    "thick",
    "babyboy",
    "badboy",
    "hotboy",
    "sexyboy",
    "singleboy",
    "lonelyboy",
    "lookingforboy",
    "needboy",
    "loveboy",
    "nakedboy",
    "nudeboy",
    "hawtboy",
    "smexyboy",
    "looking4boy",
    "hornyboy",
    "horneboy",
    "wetboy",
    "thicboy",
    "thickboy",
    "thikboy",
    "sexyboy",
    "nakedgirl",
    "nudegirl",
    "hawtgirl",
    "smexygirl",
    "looking4girl",
    "hornygirl",
    "hornegirl",
    "wetgirl",
    "thicgirl",
    "thickgirl",
    "thikgirl",
    "sexygirl",
    "babygirl",
    "badgirl",
    "hotgirl",
    "sexygirl",
    "singlegirl",
    "lonelygirl",
    "lookingforgirl",
    "needgirl",
    "lovegirl",
    "nakedbaby",
    "nudebaby",
    "popularbaby",
    "hawtbaby",
    "smexybaby",
    "interestingbaby",
    "looking4baby",
    "hornybaby",
    "hornebaby",
    "wetbaby",
    "thicbaby",
    "thickbaby",
    "thikbaby",
    "jealousbaby",
    "sexybaby",
    "babybaby",
    "badbaby",
    "hotbaby",
    "sexybaby",
    "singlebaby",
    "lonelybaby",
    "lookingforbaby",
    "needbaby",
    "lovebaby",
    "nakedmilf",
    "nudemilf",
    "popularmilf",
    "hawtmilf",
    "smexymilf",
    "interestingmilf",
    "looking4milf",
    "hornymilf",
    "hornemilf",
    "wetmilf",
    "thicmilf",
    "thickmilf",
    "thikmilf",
    "jealousmilf",
    "sexymilf",
    "babymilf",
    "badmilf",
    "hotmilf",
    "sexymilf",
    "singlemilf",
    "lonelymilf",
    "lookingformilf",
    "needmilf",
    "lovemilf",
    "nakeddilf",
    "nudedilf",
    "populardilf",
    "hawtdilf",
    "smexydilf",
    "interestingdilf",
    "looking4dilf",
    "hornydilf",
    "hornedilf",
    "wetdilf",
    "thicdilf",
    "thickdilf",
    "thikdilf",
    "jealousdilf",
    "sexydilf",
    "babydilf",
    "baddilf",
    "hotdilf",
    "sexydilf",
    "singledilf",
    "lonelydilf",
    "lookingfordilf",
    "needdilf",
    "lovedilf",
    "nakedgilf",
    "nudegilf",
    "populargilf",
    "hawtgilf",
    "smexygilf",
    "interestinggilf",
    "looking4gilf",
    "hornygilf",
    "hornegilf",
    "wetgilf",
    "thicgilf",
    "thickgilf",
    "thikgilf",
    "jealousgilf",
    "sexygilf",
    "babygilf",
    "badgilf",
    "hotgilf",
    "sexygilf",
    "singlegilf",
    "lonelygilf",
    "lookingforgilf",
    "needgilf",
    "lovegilf",
    "noobsicle",
    "daddy",
    "dxddy",
    "poop",
    "peepee",
    "peepeepoopoo",
    "buttcheek",
    "buttcheeks",
    "fotsmel",
    "miney",
    "fetsmel" 
]
}
